scopesim_targets/__init__.py
scopesim_targets/point_source.py
scopesim_targets/target.py
scopesim_targets/TEMP_pntsrc.py
scopesim_targets/typing_utils.py
scopesim_targets/yaml_constructors.py
scopesim_targets-0.1.0.dist-info/LICENSE
scopesim_targets-0.1.0.dist-info/METADATA
scopesim_targets-0.1.0.dist-info/WHEEL
scopesim_targets-0.1.0.dist-info/RECORD
