Metadata-Version: 2.3
Name: scopesim-targets
Version: 0.1.0
Summary: Definition of on-sky targets for the ScopeSim telescope observation simulator.
License: GPL-3.0-or-later
Author: Fabian Haberhauer
Author-email: fabian.haberhauer@univie.ac.at
Requires-Python: >=3.10, <3.14
Classifier: License :: OSI Approved :: GNU General Public License v3 or later (GPLv3+)
Classifier: Programming Language :: Python :: 3
Classifier: Programming Language :: Python :: 3.10
Classifier: Programming Language :: Python :: 3.11
Classifier: Programming Language :: Python :: 3.12
Classifier: Programming Language :: Python :: 3.13
Provides-Extra: scopesim
Requires-Dist: astar-utils (>=0.3.3)
Requires-Dist: astropy (>=6.1.7,<8.0.0)
Requires-Dist: matplotlib (>=3.10.1,<3.11.0)
Requires-Dist: numpy (>=1.26.4,<2.3.0)
Requires-Dist: pyyaml (>=6.0.2,<7.0.0)
Requires-Dist: scipy (>=1.15.3,<1.16.0)
Requires-Dist: scopesim (>=0.11.0,<1.0.0) ; extra == "scopesim"
Requires-Dist: spextra (>=0.42.0)
Requires-Dist: synphot (>=1.6.0,<2.0.0)
